 [
        {
            "zip": "64720",
            "type": "STANDARD",
            "decommissioned": "0",
            "primary_city": "Adrian",
            "state": "MO",
            "county": "Bates County",
            "timezone": "America/Chicago",
            "area_codes": "660, 816",
            "world_region": "NA",
            "country": "US",
            "latitude": "38.39",
            "longitude": "-94.35",
            "irs_estimated_population": "3610"
        },
        {
            "zip": "63730",
            "type": "STANDARD",
            "decommissioned": "0",
            "primary_city": "Advance",
            "unacceptable_cities": "Greenbrier",
            "state": "MO",
            "county": "Stoddard County",
            "timezone": "America/Chicago",
            "area_codes": "573",
            "world_region": "NA",
            "country": "US",
            "latitude": "37.1",
            "longitude": "-89.91",
            "irs_estimated_population": "2700"
        },
        {
            "zip": "64401",
            "type": "STANDARD",
            "decommissioned": "0",
            "primary_city": "Agency",
            "state": "MO",
            "county": "Buchanan County",
            "timezone": "America/Chicago",
            "area_codes": "816",
            "world_region": "NA",
            "country": "US",
            "latitude": "39.65",
            "longitude": "-94.74",
            "irs_estimated_population": "1480"
        },
        {
            "zip": "64830",
            "type": "PO BOX",
            "decommissioned": "0",
            "primary_city": "Alba",
            "state": "MO",
            "county": "Jasper County",
            "timezone": "America/Chicago",
            "area_codes": "417",
            "world_region": "NA",
            "country": "US",
            "latitude": "37.23",
            "longitude": "-94.41",
            "irs_estimated_population": "657"
        },
        {
            "zip": "64402",
            "type": "STANDARD",
            "decommissioned": "0",
            "primary_city": "Albany",
            "unacceptable_cities": "Gentryville",
            "state": "MO",
            "county": "Gentry County",
            "timezone": "America/Chicago",
            "area_codes": "660",
            "world_region": "NA",
            "country": "US",
            "latitude": "40.24",
            "longitude": "-94.33",
            "irs_estimated_population": "2050"
        },
        {
            "zip": "65601",
            "type": "STANDARD",
            "decommissioned": "0",
            "primary_city": "Aldrich",
            "state": "MO",
            "county": "Polk County",
            "timezone": "America/Chicago",
            "area_codes": "417",
            "world_region": "NA",
            "country": "US",
            "latitude": "37.54",
            "longitude": "-93.55",
            "irs_estimated_population": "730"
        },
        {
            "zip": "63430",
            "type": "STANDARD",
            "decommissioned": "0",
            "primary_city": "Alexandria",
            "unacceptable_cities": "Saint Francisville",
            "state": "MO",
            "county": "Clark County",
            "timezone": "America/Chicago",
            "area_codes": "217, 319, 447, 660",
            "world_region": "NA",
            "country": "US",
            "latitude": "40.39",
            "longitude": "-91.54",
            "irs_estimated_population": "460"
        },
        {
            "zip": "64420",
            "type": "PO BOX",
            "decommissioned": "0",
            "primary_city": "Allendale",
            "state": "MO",
            "county": "Worth County",
            "timezone": "America/Chicago",
            "area_codes": "660",
            "world_region": "NA",
            "country": "US",
            "latitude": "40.49",
            "longitude": "-94.29",
            "irs_estimated_population": "0"
        },
        {
            "zip": "63001",
            "type": "PO BOX",
            "decommissioned": "1",
            "primary_city": "Allenton",
            "state": "MO",
            "county": "St. Louis County",
            "timezone": "America/Chicago",
            "area_codes": "636",
            "world_region": "NA",
            "country": "US",
            "latitude": "38.5",
            "longitude": "-90.67",
            "irs_estimated_population": "56"
        },
        {
            "zip": "64001",
            "type": "STANDARD",
            "decommissioned": "0",
            "primary_city": "Alma",
            "state": "MO",
            "county": "Lafayette County",
            "timezone": "America/Chicago",
            "area_codes": "660",
            "world_region": "NA",
            "country": "US",
            "latitude": "39.09",
            "longitude": "-93.54",
            "irs_estimated_population": "610"
        },
        {
            "zip": "64620",
            "type": "STANDARD",
            "decommissioned": "0",
            "primary_city": "Altamont",
            "state": "MO",
            "county": "Daviess County",
            "timezone": "America/Chicago",
            "area_codes": "660",
            "world_region": "NA",
            "country": "US",
            "latitude": "39.88",
            "longitude": "-94.08",
            "irs_estimated_population": "380"
        },
        {
            "zip": "63732",
            "type": "STANDARD",
            "decommissioned": "0",
            "primary_city": "Altenburg",
            "acceptable_cities": "New Wells",
            "state": "MO",
            "county": "Perry County",
            "timezone": "America/Chicago",
            "area_codes": "573",
            "world_region": "NA",
            "country": "US",
            "latitude": "37.63",
            "longitude": "-89.58",
            "irs_estimated_population": "800"
        },
        {
            "zip": "65606",
            "type": "STANDARD",
            "decommissioned": "0",
            "primary_city": "Alton",
            "state": "MO",
            "county": "Oregon County",
            "timezone": "America/Chicago",
            "area_codes": "417, 573",
            "world_region": "NA",
            "country": "US",
            "latitude": "36.69",
            "longitude": "-91.39",
            "irs_estimated_population": "2640"
        },
        {
            "zip": "64421",
            "type": "STANDARD",
            "decommissioned": "0",
            "primary_city": "Amazonia",
            "state": "MO",
            "county": "Andrew County",
            "timezone": "America/Chicago",
            "area_codes": "660, 785, 816",
            "world_region": "NA",
            "country": "US",
            "latitude": "39.91",
            "longitude": "-94.94",
            "irs_estimated_population": "770"
        },
        {
            "zip": "64422",
            "type": "STANDARD",
            "decommissioned": "0",
            "primary_city": "Amity",
            "state": "MO",
            "county": "DeKalb County",
            "timezone": "America/Chicago",
            "area_codes": "816",
            "world_region": "NA",
            "country": "US",
            "latitude": "39.89",
            "longitude": "-94.49",
            "irs_estimated_population": "270"
        },
        {
            "zip": "64722",
            "type": "STANDARD",
            "decommissioned": "0",
            "primary_city": "Amoret",
            "state": "MO",
            "county": "Bates County",
            "timezone": "America/Chicago",
            "area_codes": "660, 913",
            "world_region": "NA",
            "country": "US",
            "latitude": "38.25",
            "longitude": "-94.58",
            "irs_estimated_population": "450"
        },
        {
            "zip": "64723",
            "type": "STANDARD",
            "decommissioned": "0",
            "primary_city": "Amsterdam",
            "state": "MO",
            "county": "Bates County",
            "timezone": "America/Chicago",
            "area_codes": "660, 816, 913",
            "world_region": "NA",
            "country": "US",
            "latitude": "38.34",
            "longitude": "-94.58",
            "irs_estimated_population": "510"
        },
        {
            "zip": "63431",
            "type": "STANDARD",
            "decommissioned": "0",
            "primary_city": "Anabel",
            "state": "MO",
            "county": "Macon County",
            "timezone": "America/Chicago",
            "area_codes": "660",
            "world_region": "NA",
            "country": "US",
            "latitude": "39.74",
            "longitude": "-92.31",
            "irs_estimated_population": "320"
        },
        {
            "zip": "64831",
            "type": "STANDARD",
            "decommissioned": "0",
            "primary_city": "Anderson",
            "state": "MO",
            "county": "McDonald County",
            "timezone": "America/Chicago",
            "area_codes": "417, 539, 918",
            "world_region": "NA",
            "country": "US",
            "latitude": "36.65",
            "longitude": "-94.44",
            "irs_estimated_population": "5360"
        },
        {
            "zip": "63330",
            "type": "STANDARD",
            "decommissioned": "0",
            "primary_city": "Annada",
            "state": "MO",
            "county": "Pike County",
            "timezone": "America/Chicago",
            "area_codes": "573, 618",
            "world_region": "NA",
            "country": "US",
            "latitude": "39.26",
            "longitude": "-90.82",
            "irs_estimated_population": "140"
        },
        {
            "zip": "63620",
            "type": "STANDARD",
            "decommissioned": "0",
            "primary_city": "Annapolis",
            "acceptable_cities": "Glover",
            "state": "MO",
            "county": "Iron County",
            "timezone": "America/Chicago",
            "area_codes": "573",
            "world_region": "NA",
            "country": "US",
            "latitude": "37.35",
            "longitude": "-90.69",
            "irs_estimated_population": "1030"
        },
        {
            "zip": "63820",
            "type": "PO BOX",
            "decommissioned": "0",
            "primary_city": "Anniston",
            "state": "MO",
            "county": "Mississippi County",
            "timezone": "America/Chicago",
            "area_codes": "573",
            "world_region": "NA",
            "country": "US",
            "latitude": "36.82",
            "longitude": "-89.32",
            "irs_estimated_population": "224"
        },
        {
            "zip": "64724",
            "type": "STANDARD",
            "decommissioned": "0",
            "primary_city": "Appleton City",
            "state": "MO",
            "county": "St. Clair County",
            "timezone": "America/Chicago",
            "area_codes": "417, 660",
            "world_region": "NA",
            "country": "US",
            "latitude": "38.19",
            "longitude": "-94.03",
            "irs_estimated_population": "1440"
        },
        {
            "zip": "63432",
            "type": "STANDARD",
            "decommissioned": "0",
            "primary_city": "Arbela",
            "state": "MO",
            "county": "Scotland County",
            "timezone": "America/Chicago",
            "area_codes": "660",
            "world_region": "NA",
            "country": "US",
            "latitude": "40.46",
            "longitude": "-92.01",
            "irs_estimated_population": "460"
        },
        {
            "zip": "63821",
            "type": "STANDARD",
            "decommissioned": "0",
            "primary_city": "Arbyrd",
            "state": "MO",
            "county": "Dunklin County",
            "timezone": "America/Chicago",
            "area_codes": "573, 870",
            "world_region": "NA",
            "country": "US",
            "latitude": "36.05",
            "longitude": "-90.24",
            "irs_estimated_population": "520"
        }
    ]
